MulticoreTSNE/__init__.py
MulticoreTSNE/libtsne_multicore.so
MulticoreTSNE/tests/__init__.py
MulticoreTSNE/tests/test_base.py
MulticoreTSNE-0.0.1.1.dist-info/DESCRIPTION.rst
MulticoreTSNE-0.0.1.1.dist-info/METADATA
MulticoreTSNE-0.0.1.1.dist-info/RECORD
MulticoreTSNE-0.0.1.1.dist-info/WHEEL
MulticoreTSNE-0.0.1.1.dist-info/metadata.json
MulticoreTSNE-0.0.1.1.dist-info/top_level.txt
